data/__init__.py
data/preprare_data.py
model/__init__.py
model/base_model.py
model/xgboost.py
odct_data/__init__.py
odct_data/preprare_data.py
odct_model/__init__.py
odct_model/base_model.py
odct_model/xgboost.py
data_product_model-0.0.1.dist-info/LICENSE
data_product_model-0.0.1.dist-info/METADATA
data_product_model-0.0.1.dist-info/WHEEL
data_product_model-0.0.1.dist-info/top_level.txt
data_product_model-0.0.1.dist-info/RECORD
