Metadata-Version: 2.1
Name: data-product-model
Version: 0.0.1
Summary: Data Product tools for optimizing model
Home-page: https://github.com/anhtranhoang/data-product-model
Author: Tran Hoang Anh
Author-email: anh.tran14@onemount.com
License: UNKNOWN
Platform: UNKNOWN
Classifier: Programming Language :: Python :: 3
Classifier: License :: OSI Approved :: MIT License
Classifier: Operating System :: OS Independent
Requires-Python: >=3.6
